formspec/__init__.py
formspec-0.0.1.dist-info/licenses/LICENSE
formspec-0.0.1.dist-info/METADATA
formspec-0.0.1.dist-info/WHEEL
formspec-0.0.1.dist-info/top_level.txt
formspec-0.0.1.dist-info/RECORD
